mason_server/__init__.py
mason_server-0.0.0.dist-info/LICENSE
mason_server-0.0.0.dist-info/WHEEL
mason_server-0.0.0.dist-info/METADATA
mason_server-0.0.0.dist-info/RECORD
