Metadata-Version: 2.1
Name: mason-server
Version: 0.0.0
Summary: Backend server for mason framework.
Requires-Python: >=3.7,<4.0
Classifier: Programming Language :: Python :: 3
Classifier: Programming Language :: Python :: 3.7
Classifier: Programming Language :: Python :: 3.8
Requires-Dist: importlib-metadata (>=1.6.0,<2.0.0)
Requires-Dist: mason-framework (>=0.0.3,<0.0.4)
